pytest_gradescope/__init__.py
pytest_gradescope/decorators.py
pytest_gradescope/pytest_plugin.py
pytest_gradescope-0.1.6.dist-info/METADATA
pytest_gradescope-0.1.6.dist-info/WHEEL
pytest_gradescope-0.1.6.dist-info/entry_points.txt
pytest_gradescope-0.1.6.dist-info/top_level.txt
pytest_gradescope-0.1.6.dist-info/RECORD
