Metadata-Version: 2.4
Name: pytest-gradescope
Version: 0.1.6
Summary: A pytest plugin for Gradescope integration
Author: Sebastian Ingino
Author-email: sebastian@ingino.me
License: MIT
Classifier: Framework :: Pytest
Dynamic: author
Dynamic: author-email
Dynamic: classifier
Dynamic: description
Dynamic: description-content-type
Dynamic: license
Dynamic: summary
